{
  "site": "CRA (Canada Revenue Agency)",
  "site_url": "https://www.canada.ca/en/revenue-agency.html",
  "category": "express_entry",
  "page_url": "https://www.canada.ca/en/revenue-agency/services/e-services/digital-services-individuals/efile-electronic-filers/detailed-information-taxtron.html",
  "title": "Detailed information for TaxTron Inc. - Canada.ca",
  "crawled_at": "2026-06-11T12:22:26.737297+07:00",
  "content": "\n## Detailed information for TaxTron Inc.\nProduct name: Taxtron Win Pro\nCertified for the 2025 tax year: Yes Certified for prior years 2018, 2019, 2020, 2021, 2022, 2023 and 2024: Yes\nAddress: 2292 Islington Ave, Etobicoke, ON, M9W 3W8\nSupport: TaxTron Help Telephone: 1-416-491-0333\nExclusions for the 2025 tax year.\n- Form T1134, Information Return Relating to Controlled and Non-Controlled Foreign Affiliates\n- Form T2203, Provincial and Territorial Taxes – Multiple Jurisdictions\n- Electronic transmission of Form T217 Election, or Revocation of an Election, to use the Mark-to-Market method\n- Electronic transmission of Form T2057 Election on Disposition of Property by a Taxpayer to a Taxable Canadian Corporation\n- Electronic transmission of Form T2059 Election on Disposition of Property by a Taxpayer to a Canadian Partnership\n- Submit Documents web service for T217, T2057, and T2059 attachments\n- Non-Resident Status Returns - Deemed Resident\n- Limited occurrences of Crop Inventory valuation and productive capacity and Livestock inventory valuation on Form T1273\nExclusions for the 2024 tax year.\n- Form T1134, Information Return Relating to Controlled and Non-Controlled Foreign Affiliates\n- Form T2203, Provincial and Territorial Taxes – Multiple Jurisdictions\n- Electronic transmission of Form T217 Election, or Revocation of an Election, to use the Mark-to-Market method\n- Electronic transmission of Form T2057 Election on Disposition of Property by a Taxpayer to a Taxable Canadian Corporation\n- Electronic transmission of Form T2059 Election on Disposition of Property by a Taxpayer to a Canadian Partnership\n- Submit Documents web service for T217, T2057, and T2059 attachments\n- Limited occurrences of Crop Inventory valuation and productive capacity and Livestock inventory valuation on Form T1273\n- Non-Resident Status Returns - Deemed Resident\nExclusions for the 2023 tax year.\n- Form T1134, Information Return Relating to Controlled and Non-Controlled Foreign Affiliates\n- Form T2203, Provincial and Territorial Taxes – Multiple Jurisdictions\n- Electronic transmission of Form T217 Election, or Revocation of an Election, to use the Mark-to-Market method\n- Electronic transmission of Form T2057 Election on Disposition of Property by a Taxpayer to a Taxable Canadian Corporation\n- Electronic transmission of Form T2059 Election on Disposition of Property by a Taxpayer to a Canadian Partnership\n- Limited occurrences of Crop Inventory valuation and productive capacity and Livestock inventory valuation on Form T1273\n- Electronic transmission of Form UHT-2900 - Underused Housing Tax Return and Election Form\n- Non-Resident Status Returns - Deemed Resident\nExclusions for the 2022 tax year.\n- Form T1134, Information Return Relating to Controlled and Non-Controlled Foreign Affiliates\n- Form T2203, Provincial and Territorial Taxes – Multiple Jurisdictions\nExclusions for the 2021 tax year.\n- Form T1134, Information Return Relating to Controlled and Non-Controlled Foreign Affiliates\n- Form T2203, Provincial and Territorial Taxes - Multiple Jurisdictions\n- Limitation of 15 occurrences of Section 7 and 8 in form T1273\nExclusions for the 2018, 2019 and 2020 tax years.\n- Form T2203, Provincial and Territorial Taxes - Multiple Jurisdictions\n- Limitation of 15 occurrences of Section 7 and 8 in form T1273\n*Disclaimer Please note that this information was provided by the software developer. If you find any discrepancies in the information provided, please contact the software developer directly. The links are provided for your convenience and are to be used at your own discretion.\nProduct name: Taxtron Mac Pro\nCertified for the 2025 tax year: Yes Certified for prior years 2018, 2019, 2020, 2021, 2022, 2023 and 2024: Yes\nAddress: 2292 Islington Ave, Etobicoke, ON, M9W 3W8\nSupport: TaxTron Help\nTelephone: 1-416-491-0333\nExclusions for the 2025 tax year.\n- Form T1134, Information Return Relating to Controlled and Non-Controlled Foreign Affiliates\n- Form T2203, Provincial and Territorial Taxes – Multiple Jurisdictions\n- Electronic transmission of Form T217 Election, or Revocation of an Election, to use the Mark-to-Market method\n- Electronic transmission of Form T2057 Election on Disposition of Property by a Taxpayer to a Taxable Canadian Corporation\n- Electronic transmission of Form T2059 Election on Disposition of Property by a Taxpayer to a Canadian Partnership\n- Submit Documents web service for T217, T2057, and T2059 attachments\n- Non-Resident Status Returns - Deemed Resident\n- Limited occurrences of Crop Inventory valuation and productive capacity and Livestock inventory valuation on Form T1273\nExclusions for the 2024 tax year .\n- Form T1134, Information Return Relating to Controlled and Non-Controlled Foreign Affiliates\n- Form T2203, Provincial and Territorial Taxes – Multiple Jurisdictions\n- Electronic transmission of Form T217 Election, or Revocation of an Election, to use the Mark-to-Market method\n- Electronic transmission of Form T2057 Election on Disposition of Property by a Taxpayer to a Taxable Canadian Corporation\n- Electronic transmission of Form T2059 Election on Disposition of Property by a Taxpayer to a Canadian Partnership\n- Submit Documents web service for T217, T2057, and T2059 attachments\n- Limited occurrences of Crop Inventory valuation and productive capacity and Livestock inventory valuation on Form T1273\n- Non-Resident Status Returns - Deemed Resident\n- Electronic transmission of Form UHT-2900 - Underused Housing Tax Return and Election Form\nExclusions for the 2023 tax year.\n- Form T1134, Information Return Relating to Controlled and Non-Controlled Foreign Affiliates\n- Form T2203, Provincial and Territorial Taxes – Multiple Jurisdictions\n- Electronic transmission of Form T217 Election, or Revocation of an Election, to use the Mark-to-Market method\n- Electronic transmission of Form T2057 Election on Disposition of Property by a Taxpayer to a Taxable Canadian Corporation\n- Electronic transmission of Form T2059 Election on Disposition of Property by a Taxpayer to a Canadian Partnership\n- Limited occurrences of Crop Inventory valuation and productive capacity and Livestock inventory valuation on Form T1273\n- Electronic transmission of Form UHT-2900 - Underused Housing Tax Return and Election Form\n- Non-Resident Status Returns - Deemed Resident\nExclusions for the 2022 tax year.\n- Form T1134, Information Return Relating to Controlled and Non-Controlled Foreign Affiliates\n- Form T2203, Provincial and Territorial Taxes – Multiple Jurisdictions\nExclusions for the 2021 tax year.\n- Form T1134, Information Return Relating to Controlled and Non-Controlled Foreign Affiliates\n- Form T2203, Provincial and Territorial Taxes - Multiple Jurisdictions\n- Limitation of 15 occurrences of Section 7 and 8 in form T1273\nExclusions for the 2018, 2019 and 2020 tax years.\n- Form T2203, Provincial and Territorial Taxes - Multiple Jurisdictions\n- Limitation of 15 occurrences of Section 7 and 8 in form T1273\n*Disclaimer Please note that this information was provided by the software developer. If you find any discrepancies in the information provided, please contact the software developer directly. The links are provided for your convenience and are to be used at your own discretion.\nProduct name: Taxtron Web\nCertified for the 2025 tax year: Yes Certified for prior years 2018, 2019, 2020, 2021, 2022, 2023 and 2024: Yes\nAddress: 2292 Islington Ave, Etobicoke, ON, M9W 3W8\nSupport: TaxTron Help Telephone: 1-416-491-0333\nExclusions for the 2025 tax year.\n- Form T1134, Information Return Relating to Controlled and Non-Controlled Foreign Affiliates\n- Form T2203, Provincial and Territorial Taxes - Multiple Jurisdictions\n- Electronic transmission of Form T217 Election, or Revocation of an Election, to use the Mark-to-Market method\n- Electronic transmission of Form T2057 Election on Disposition of Property by a Taxpayer to a Taxable Canadian Corporation\n- Electronic transmission of Form T2059 Election on Disposition of Property by a Taxpayer to a Canadian Partnership\n- Submit Documents web service for T217, T2057, and T2059 attachments\n- Non-Resident Status Returns - Deemed Resident\n- Limited occurrences of Crop Inventory valuation and productive capacity and Livestock inventory valuation on Form T1273\nExclusions for the 2024 tax year.\n- Form T1134, Information Return Relating to Controlled and Non-Controlled Foreign Affiliates\n- Form T2203, Provincial and Territorial Taxes - Multiple Jurisdictions\n- Electronic transmission of Form T217 Election, or Revocation of an Election, to use the Mark-to-Market method\n- Electronic transmission of Form T2057 Election on Disposition of Property by a Taxpayer to a Taxable Canadian Corporation\n- Electronic transmission of Form T2059 Election on Disposition of Property by a Taxpayer to a Canadian Partnership\n- Submit Documents web service for T217, T2057, and T2059 attachments\n- Limited occurrences of Crop Inventory valuation and productive capacity and Livestock inventory valuation on Form T1273\n- Non-Resident Status Returns - Deemed Resident\nExclusions for the 2023 tax year.\n- Form T1134, Information Return Relating to Controlled and Non-Controlled Foreign Affiliates\n- Form T2203, Provincial and Territorial Taxes - Multiple Jurisdictions\n- Electronic transmission of Form T217 Election, or Revocation of an Election, to use the Mark-to-Market method\n- Electronic transmission of Form T2057 Election on Disposition of Property by a Taxpayer to a Taxable Canadian Corporation\n- Electronic transmission of Form T2059 Election on Disposition of Property by a Taxpayer to a Canadian Partnership\n- Limited occurrences of Crop Inventory valuation and productive capacity and Livestock inventory valuation on Form T1273\n- Electronic transmission of Form UHT-2900 - Underused Housing Tax Return and Election Form\n- Non-Resident Status Returns - Deemed Resident\nExclusions for the 2022 tax year.\n- Form T1134, Information Return Relating to Controlled and Non-Controlled Foreign Affiliates\n- Form T2203, Provincial and Territorial Taxes - Multiple Jurisdictions\nExclusions for the 2021 tax year.\n- Form T1134, Information Return Relating to Controlled and Non-Controlled Foreign Affiliates\n- Form T2203, Provincial and Territorial Taxes - Multiple Jurisdictions\n- Limitation of 15 occurrences of Section 7 and 8 in form T1273\nExclusions for the 2019 and 2020 tax years.\n- Form T2203, Provincial and Territorial Taxes - Multiple Jurisdictions\n- Limitation of 15 occurrences of Section 7 and 8 in form T1273\nExclusions for the 2018 tax year.\n- Form T2203, Provincial and Territorial Taxes - Multiple Jurisdictions\n- Limitation of 15 occurrences of Section 7 and 8 in form T1273\n- Pre-Authorized Debit (PAD)\n*Disclaimer Please note that this information was provided by the software developer. If you find any discrepancies in the information provided, please contact the software developer directly. The links are provided for your convenience and are to be used at your own discretion.\n\n### Give feedback about this page\nThank you for your feedback.",
  "structured_data": {},
  "status": "ok",
  "error": null
}