{
  "site": "Data.govt.nz (Open Data NZ)",
  "site_url": "https://data.govt.nz",
  "category": "open_data",
  "page_url": "https://data.govt.nz/toolkit/data-ethics/government-algorithm-transparency-and-accountability/algorithm-assessment-report",
  "title": "Algorithm assessment report 2018\n\t - data.govt.nz",
  "crawled_at": "2026-06-11T15:23:02.000826+07:00",
  "content": "\n## Algorithm assessment report 2018\nA cross-government review of how government uses algorithms to improve the lives of New Zealanders was undertaken in 2018. The review aimed to ensure New Zealanders are informed, and have confidence in how the government uses algorithms.\nAlgorithm assessment report - full report [HTML] Algorithm assessment report - full report [PDF 10.1 MB] Algorithm assessment report - one-page summary [PDF 151 KB]\n- Response to the algorithm report\nIn 2018, the New Zealand government undertook a review of how government agencies use algorithms to improve the lives of New Zealanders. Led by the Government Chief Data Steward and Government Chief Digital Officer, the review initially focused on operational algorithms that result in, or inform, decisions that directly impact people or groups.\nGovernment Chief Data Steward Government Chief Digital Officer\nFourteen government agencies self-assessed the algorithms they use to deliver their functions, focussing on areas most directly impacting decisions related to people.\nThe 'Algorithm assessment report' summarises these self-assessments. The report aims to ensure New Zealanders are informed about the use of government algorithms and the checks and balances that exist to manage their use.\nThe report drew on the ‘Principles for safe and effective use of data and analytics’ developed by the Privacy Commissioner and the Government Chief Data Steward and made recommendations to improve transparency and accountability in government algorithm use.\nPrinciples for safe and effective use of data and analytics\n\n## Response to the algorithm assessment report\nResponding to the recommendations from the report, in 2020 the Government Chief Data Steward has:\n- released the ‘Algorithm charter for Aotearoa New Zealand’ in which signing agencies make a public commitment to the transparent and accountable use of algorithms.\n- ensured that government agencies can seek external advice from privacy, ethics, and data experts by continuing to convene the independent Data Ethics Advisory Group.\n- continued work to ensure that data ethics are embedded at all levels of the government analytics workforce, through improvements in training and professional development for data analysts and decision makers.\nResponding to the algorithm assessment [PDF 201KB]\nResponding to the algorithm assessment [HTML]\nData Ethics Advisory Group [HTML]\nThese documents provide more information on the process used to produce the Algorithm assessment report.\n- Commissioning the work – Report: Review of Government algorithms\n- Agency submissions: Algorithm assessment agency submissions: June – July 2018\nReport: Review of Government algorithms [PDF 749 KB] Algorithm assessment agency submissions: June – July 2018 [PDF 1.68 MB]\nSome documents contain redacted information under the following sections of the Official Information Act 1982:\n- 9(2)(a) to protect the privacy of natural persons.\n- 9(2)(f)(iv) to maintain the confidentiality of advice tendered by Ministers of the Crown and officials.\nIn preparing this information release, Stats NZ considered the public interest considerations in section 9(1) of the Official Information Act.\nOfficial Information Act 1982\nThe Algorithm Charter Blog: Algorithm review underway to increase transparency and accountability (18 July 2018) Media release: Government to undertake urgent algorithm stocktake 923 May 2018) Media release: Government will move quickly on AI action plan (2 May 2018)\nAlgorithms have an essential role in supporting the services that government provides to people in New Zealand and to help deliver new, innovative, and well targeted policies to achieve government aims.\n- 3.7 million people pay Pay As You Earn (PAYE) tax or file a personal tax return.\n- 277,410 people receive working age benefits and 753,319 receive New Zealand Superannuation.\n- More than 700,000 people are referred for specialist surgery.\n- There are around 2 million accident compensation claims.\n- More than 1.5 million children, young people, and students enrol in the education system.\n- 158,900 referrals about children at risk are made, and further action was needed in 33,000 cases.\n- 41 million mail items and 496,000 import sea containers are screened, and 13.9 million travellers are assessed at the border.\n- More than 1.1 million events are responded to by the police, and more than 100,000 cases are prosecuted.\nThe report presents an assessment of information reported by 14 government agencies about the computer algorithms they use to deliver their functions. It focuses on algorithms that are used in decision-making processes that affect people in direct and significant ways.\n\n### Key findings and recommendations\n- Humans, rather than computers, review and decide on almost all significant decisions made by government agencies. As agencies continue to develop new algorithms, it’s important to preserve appropriate human oversight and ensure that the views of key stakeholders, notably the people who will receive or participate in services, are given appropriate consideration.\n- While agencies are applying a range of safeguards and assurance processes in relation to their algorithms use, there are opportunities for increased collaboration and sharing of good practice across government.\n- There is also scope to ensure that all of the information that is published explains, in clear and simple terms, how algorithms are informing decisions that affect people in significant ways.\n- The government commitment to Treaty-based partnership should also be reflected, embedding a te ao Māori perspective into the development and use of algorithms.\n- In addition to connecting expertise across government, agencies could also benefit from a fresh perspective by looking beyond government for privacy, ethics, and data expertise. This could be achieved by bringing together a group of independent experts that agencies could consult for advice and guidance.\nIf you’d like more information, have a question, or want to provide feedback, email datalead@stats.govt.nz .\nContent last reviewed 15 June 2023.",
  "structured_data": {},
  "status": "ok",
  "error": null
}