{
  "site": "Greenberg Traurig (GT Law)",
  "site_url": "https://gtlaw.com",
  "category": "eb3_perm",
  "page_url": "https://gtlaw.com/en/events/2026/07/florida-chambers-40th-annual-environmental-permitting-summer-school-conference",
  "title": "Florida Chamber's 40th Annual Environmental Permitting Summer School Conference | Events | Greenberg Traurig LLP",
  "crawled_at": "2026-06-08T13:13:20.572640+07:00",
  "content": "As part of the Florida Chamber Foundation’s ongoing effort to keep its members and other business organizations informed of the numerous environmental and growth management laws and regulations affecting Florida’s citizens and businesses, the Environmental Permitting Summer School Conference is a seminar for Florida’s environmental and growth management audience. Celebrating its 40th anniversary, this longtime program continues to serve as one of the state’s leading educational forums focused on identifying solutions to challenges facing Florida. The programs feature a unique “break-out” format and are substantially revised and updated each year to afford the most advanced and current instruction available on Florida’s environmental, energy, and growth management laws, rules, and programs, while also providing opportunities for professional development, continuing education, and networking within Florida’s environmental community.\nSchedule for our GT Attorneys speaking:\nJulie P. Kendig-Schrader : Wednesday, July 22, 2026 at 8:30 am to 10:10 am EDT, Venue: Calusa 4-5\nBernadette M. Rappold: Wednesday, July 22, 2026 at 10:30 am - 12:10 pm EDT, Venue: Calusa 4-5\nKerri L. Barsh: Thursday, July 23, 2026 at 8:30 am to 10:10 am EDT, Venue: Calusa 2-3\nJohn V. Chibbaro : Thursday, July 23, 2026 at 8:30 am to 10:10 am EDT, Venue: Calusa 11\nBernadette M. Rappold : Thursday, July 23, 2026 at 10:30 am to 12:10 pm EDT, Venue: Calusa 4-5\nMaribel Nicholson-Choice: Thursday, July 23, 2026 at 1:30 pm to 3:10 pm EDT, Venue: Calusa 12\nJulie P. Kendig-Schrader: Thursday, July 23, 2026 at 3:30 pm to 5:10 pm EDT, Venue: Calusa 4-5\nChris Torres : Friday, July 24, 2026 at 8:30 am to 10:10 am EDT, Venue: Calusa 8-9\nFor full schedule and speakers, please review here Click Here",
  "structured_data": {},
  "status": "ok",
  "error": null
}