{
  "site": "Green and Spiegel LLP",
  "site_url": "https://www.gands.com",
  "category": "startup_business",
  "page_url": "https://gands.com/en-us/u-s-immigration/business-immigration/visa-information/e-3-visas/",
  "title": "E-3 Visas - Green & Spiegel",
  "crawled_at": "2026-06-11T15:00:28.520594+07:00",
  "content": "Home > U.S Immigration-2 > U.S. Immigration > Business Immigration > Visa Information > E-3 Visas\n\n## What is an E-3 Visa?\nThe E-3 visa, which was created in 2005 in connection with a free trade agreement between the United States and Australia, is available to appropriately-qualified Australian nationals who will work in a qualifying “specialty occupation” in the United States. There is also an E-3D visa classification for dependents, and spouses are eligible to obtain employment authorization.\nE-3 Visas are available in two-year increments and may be renewed indefinitely, but do require their holders to have 100% nonimmigrant intent, meaning that E-3 Applicants must attest to the fact that they do not intend to abandon their residence outside the United States.\nGreen and Spiegel has a long history of working closely with the Australian community, with a particular focus on this specific classification, and we are well-positioned to help you and your family make the most of the many benefits it offers. Since spring 2020, we have been helping Australian nationals navigate some of the complex issues caused by the COVID-19 pandemic, whether they be Embassy/Consulate closures, travel restrictions, or job loss, and we pride ourselves on our ability to find unique solutions for unique problems.\n\n## How do you get an E-3 Visa?\nAn attractive feature of the E-3 Visa is that Australian nationals may choose to apply for them directly at a U.S. Embassy/Consulate abroad, meaning that applicants are able to bypass many of the cumbersome internal filing processes required for other classifications.\nIndividuals already in the United States may choose to instead pursue this classification by filing an internal petition with the U.S. Citizenship and Immigration Services (USCIS), which can be used to change status to E-3 from another visa classification, or to change employers when already in the United States. This process can also be used to extend an existing E-3 visa for individuals who cannot or do not want to travel abroad. While this process typically takes longer than the consular route (and involves higher government filing fees), it has become a popular option for many individuals, especially during the current pandemic.\n- Sign up for E-Alerts\n\n## Philadelphia (U.S. Head office)\n\n#### Sign up our newsletter to get update information, news and free insight.",
  "structured_data": {},
  "status": "ok",
  "error": null
}