{
  "site": "Health Canada",
  "site_url": "https://www.canada.ca/en/health-canada.html",
  "category": "health",
  "page_url": "https://www.canada.ca/en/health-canada/services/food-guide/eating-support/kitchen/cooking-skills/10-reasons-buy-frozen-vegetables-fruits.html",
  "title": "10 reasons to buy frozen vegetables and fruits - Canada.ca",
  "crawled_at": "2026-06-11T12:16:24.254327+07:00",
  "content": "\n## 10 reasons to buy frozen vegetables and fruits\nEstimated reading time: 2 minutes\n\n### 1. They're just as nutritious as fresh\nProduce is picked at its peak of freshness and frozen right away.\nTip: Use food labels to choose frozen produce with little to no added sodium, sugar, or saturated fat.\n\n### 2. You can save money\nYou can stock up on frozen produce when it's on sale. Check your local grocery store flyers and compare prices.\n\n### 3. They save you time\nThe washing and cutting are done for you. Look for frozen produce in the form that you need – whole, sliced, or chopped.\nTip: Try keeping 1 or 2 kinds of frozen vegetables and fruits on hand for quick and easy meal or snack prep.\n\n### 4. You can reduce food waste\nNeed a vegetable or fruit for a recipe, but not sure you'll use it all? Frozen produce allows you to use only what you need, and save the rest for a later date.\n\n### 5. You have more choices\nSome vegetables and fruits are not available fresh throughout the year. Buying frozen vegetables and fruits can give you more variety all year round.\n\n### 6. They have many uses\nFrozen vegetables and fruits are great for so many recipes. For example:\n- use frozen butternut squash cubes for a quick puréed soup\n- thaw frozen berries to add to your favourite muffin or loaf recipe\n- add frozen peach slices to yogurt for summer flavours during the winter\n- sauté frozen vegetables for a stir-fry, or steam and season them for a side dish\n\n### 7. They should make up half your meal\nFrozen vegetables and fruits can help you eat plenty of vegetables and fruits each day.\nFrozen produce does not spoil as quickly as fresh vegetables and fruits.\n\n### 9. They cook faster than fresh vegetables\nMany vegetables are blanched before freezing. Blanched vegetables cook quickly, saving you time.\nTip: Add frozen broccoli to a pot of boiling pasta in the last minute of cooking. Strain the broccoli and pasta, then top with your favourite pasta sauce.\n\n### 10. They're flavourful all year round\nFresh produce is frozen when its flavour is at its peak.\nThere are so many reasons to love frozen vegetables and fruit. Tell us why you love frozen produce! Write us at nutrition@hc-sc.gc.ca or reach us on social media [@healthycdns]!\n\n## More from the food guide kitchen\nHealthy cooking methods\nLimit highly processed foods\nFor recipes and more food guide resources visit: Canada.ca/FoodGuide",
  "structured_data": {},
  "status": "ok",
  "error": null
}